README.md
setup.py
cryptapi/CryptAPI.py
cryptapi/__init__.py
python_cryptapi.egg-info/PKG-INFO
python_cryptapi.egg-info/SOURCES.txt
python_cryptapi.egg-info/dependency_links.txt
python_cryptapi.egg-info/not-zip-safe
python_cryptapi.egg-info/requires.txt
python_cryptapi.egg-info/top_level.txt