Metadata-Version: 2.1
Name: python-cryptapi
Version: 1.0.3
Summary: Python Library for CryptAPI payment gateway
Home-page: https://github.com/cryptapi/python-cryptapi
Author: CryptAPI
Author-email: info@cryptapi.io
License: MIT
Classifier: Programming Language :: Python
Classifier: Development Status :: 5 - Production/Stable
Classifier: Framework :: Django
Classifier: Intended Audience :: Developers
Classifier: License :: OSI Approved :: MIT License
Classifier: Natural Language :: English
Classifier: Operating System :: OS Independent
Classifier: Programming Language :: Python :: 3
